enfusion_api/__init__.py
enfusion_api/core.py
enfusion_api-0.1.0.dist-info/LICENSE
enfusion_api-0.1.0.dist-info/METADATA
enfusion_api-0.1.0.dist-info/WHEEL
enfusion_api-0.1.0.dist-info/top_level.txt
enfusion_api-0.1.0.dist-info/RECORD
