Metadata-Version: 2.1
Name: enfusion_api
Version: 0.1.0
Summary: A package to interact with Enfusion API and retrieve data as pandas DataFrames.
Home-page: https://github.com/h1whelan/enfusion_api
Author: Henry Whelan
Author-email: henrywhelan93@gmail.com
Classifier: Development Status :: 3 - Alpha
Classifier: Intended Audience :: Developers
Classifier: License :: OSI Approved :: MIT License
Classifier: Programming Language :: Python :: 3
Classifier: Programming Language :: Python :: 3.6
Classifier: Programming Language :: Python :: 3.7
Classifier: Programming Language :: Python :: 3.8
Classifier: Programming Language :: Python :: 3.9
Classifier: Programming Language :: Python :: 3.10
Classifier: Operating System :: OS Independent
Requires-Python: >=3.6
License-File: LICENSE
Requires-Dist: requests>=2.0
Requires-Dist: pandas>=1.0
